itagger/__init__.py
itagger/anilist_client.py
itagger/cli.py
itagger/comicinfo_generator.py
itagger/models.py
itagger-0.1.2.dist-info/METADATA
itagger-0.1.2.dist-info/WHEEL
itagger-0.1.2.dist-info/entry_points.txt
itagger-0.1.2.dist-info/licenses/LICENSE
itagger-0.1.2.dist-info/RECORD
