Metadata-Version: 2.4
Name: itagger
Version: 0.1.2
Summary: CLI tool to create and embed ComicInfo.xml metadata for manga using AniList API
Project-URL: Homepage, https://github.com/FelixSiegel/itagger
Project-URL: Issues, https://github.com/FelixSiegel/itagger/issues
Project-URL: Repository, https://github.com/FelixSiegel/itagger
Author-email: InfinityCoding <infinitycoding@web.de>
License-Expression: GPL-3.0-or-later
License-File: LICENSE
Keywords: anilist,cbz,comicinfo,kavita,komga,manga,metadata
Classifier: Development Status :: 4 - Beta
Classifier: Environment :: Console
Classifier: Intended Audience :: End Users/Desktop
Classifier: License :: OSI Approved :: GNU General Public License v3 (GPLv3)
Classifier: Operating System :: OS Independent
Classifier: Programming Language :: Python :: 3
Classifier: Programming Language :: Python :: 3.13
Classifier: Topic :: Multimedia :: Graphics
Classifier: Topic :: System :: Archiving
Requires-Python: >=3.13
Requires-Dist: click>=8.1.0
Requires-Dist: lxml>=4.9.0
Requires-Dist: python-dateutil>=2.8.0
Requires-Dist: requests>=2.31.0
